AnoPrimer/__init__.py
AnoPrimer/design.py
AnoPrimer/evaluate.py
AnoPrimer/params/default.json
AnoPrimer/params/relaxed.json
AnoPrimer/params/stringent.json
AnoPrimer/utils.py
anoprimer-2.0.8.dist-info/LICENSE
anoprimer-2.0.8.dist-info/METADATA
anoprimer-2.0.8.dist-info/WHEEL
anoprimer-2.0.8.dist-info/RECORD
