Metadata-Version: 2.1
Name: AnoPrimer
Version: 2.0.8
Summary: A package to design primers in Anopheles gambiae whilst considering genetic variation with malariagen_data
Home-page: https://github.com/sanjaynagi/anoprimer
License: MIT
Author: Sanjay Nagi
Author-email: sanjay.nagi@lstmed.ac.uk
Requires-Python: >=3.10,<3.13
Classifier: License :: OSI Approved :: MIT License
Classifier: Programming Language :: Python :: 3
Classifier: Programming Language :: Python :: 3.10
Classifier: Programming Language :: Python :: 3.11
Classifier: Programming Language :: Python :: 3.12
Requires-Dist: gget
Requires-Dist: kaleido
Requires-Dist: malariagen_data (>=10.0.0)
Requires-Dist: openpyxl
Requires-Dist: primer3-py (>=2.0.0)
Requires-Dist: seaborn
Project-URL: Documentation, https://sanjaynagi.github.io/anoprimer/latest/
Project-URL: Repository, https://github.com/sanjaynagi/anoprimer
